odoo/addons/auth_ldaps/README.rst
odoo/addons/auth_ldaps/__init__.py
odoo/addons/auth_ldaps/__manifest__.py
odoo/addons/auth_ldaps/i18n/auth_ldaps.pot
odoo/addons/auth_ldaps/i18n/it.po
odoo/addons/auth_ldaps/models/__init__.py
odoo/addons/auth_ldaps/models/res_company_ldap.py
odoo/addons/auth_ldaps/readme/CONFIGURE.rst
odoo/addons/auth_ldaps/readme/CONTRIBUTORS.rst
odoo/addons/auth_ldaps/readme/DESCRIPTION.rst
odoo/addons/auth_ldaps/readme/INSTALL.rst
odoo/addons/auth_ldaps/readme/USAGE.rst
odoo/addons/auth_ldaps/static/description/icon.png
odoo/addons/auth_ldaps/static/description/index.html
odoo/addons/auth_ldaps/views/res_company_ldap_views.xml
odoo14_addon_auth_ldaps-14.0.1.0.1.dist-info/METADATA
odoo14_addon_auth_ldaps-14.0.1.0.1.dist-info/WHEEL
odoo14_addon_auth_ldaps-14.0.1.0.1.dist-info/top_level.txt
odoo14_addon_auth_ldaps-14.0.1.0.1.dist-info/RECORD
